dxf_fix/__init__.py
dxf_fix-0.1.dist-info/COPYING
dxf_fix-0.1.dist-info/METADATA
dxf_fix-0.1.dist-info/WHEEL
dxf_fix-0.1.dist-info/entry_points.txt
dxf_fix-0.1.dist-info/top_level.txt
dxf_fix-0.1.dist-info/RECORD
