Metadata-Version: 2.1
Name: dxf-fix
Version: 0.1
Summary: Fixer for dxf files like those output by openscad
Home-page: https://github.com/thatch/dxf_fix
Author: Tim Hatch
Author-email: tim@timhatch.com
License: BSD
Platform: UNKNOWN
Requires-Dist: ezdxf
